MANIFEST.in
README.txt
setup.py
collective/__init__.py
collective.contentmigrationui.egg-info/PKG-INFO
collective.contentmigrationui.egg-info/SOURCES.txt
collective.contentmigrationui.egg-info/dependency_links.txt
collective.contentmigrationui.egg-info/entry_points.txt
collective.contentmigrationui.egg-info/namespace_packages.txt
collective.contentmigrationui.egg-info/not-zip-safe
collective.contentmigrationui.egg-info/requires.txt
collective.contentmigrationui.egg-info/top_level.txt
collective/contentmigrationui/.tmp_profiles.zcml.81656~
collective/contentmigrationui/__init__.py
collective/contentmigrationui/configure.zcml
collective/contentmigrationui/interfaces.py
collective/contentmigrationui/profiles.zcml
collective/contentmigrationui/setuphandlers.py
collective/contentmigrationui/utils.py
collective/contentmigrationui/version.txt
collective/contentmigrationui/Extensions/Install.py
collective/contentmigrationui/Extensions/__init__.py
collective/contentmigrationui/allmigrations/.tmp_configure.zcml.35666~
collective/contentmigrationui/allmigrations/__init__.py
collective/contentmigrationui/allmigrations/basemigrations.py
collective/contentmigrationui/allmigrations/configure.zcml
collective/contentmigrationui/allmigrations/documentToFolderishpage.py
collective/contentmigrationui/allmigrations/documentToStructuredDocument.py
collective/contentmigrationui/allmigrations/folderToTaxonomy.py
collective/contentmigrationui/allmigrations/folderishpageToStructDoc.py
collective/contentmigrationui/allmigrations/taxonomyToFolder.py
collective/contentmigrationui/browser/.tmp_configure.zcml.11720~
collective/contentmigrationui/browser/.tmp_configure.zcml.50326~
collective/contentmigrationui/browser/.tmp_configure.zcml.58699~
collective/contentmigrationui/browser/.tmp_configure.zcml.96351~
collective/contentmigrationui/browser/.tmp_contentsmap.pt.19267~
collective/contentmigrationui/browser/__init__.py
collective/contentmigrationui/browser/configure.zcml
collective/contentmigrationui/browser/contentmigration_view.py
collective/contentmigrationui/browser/contentsmap.pt
collective/contentmigrationui/browser/filterednavtreestategy.py
collective/contentmigrationui/browser/interfaces.py
collective/contentmigrationui/browser/images/process-icon.png
collective/contentmigrationui/browser/javascript/contentsmap.js
collective/contentmigrationui/browser/templates/.tmp_confirm.pt.80751~
