Metadata-Version: 1.0
Name: collective.contentmigrationui
Version: 0.1
Summary: A content migration wizard based on Products.contentmigration
Home-page: http://pypi.python.org/pypi/collective.contentmigrationui
Author: Giacomo Spettoli
Author-email: GSpettoli@regione.emilia-romagna.it
License: GPL
Keywords: web zope plone content migration
Platform: UNKNOWN
Classifier: Development Status :: 5 - Production/Stable
Classifier: Environment :: Web Environment
Classifier: Framework :: Plone
Classifier: Framework :: Zope2
Classifier: License :: OSI Approved :: GNU General Public License (GPL)
Classifier: Operating System :: OS Independent
Classifier: Programming Language :: Python
Classifier: Topic :: Software Development :: Libraries :: Python Modules
